README.txt
setup.cfg
setup.py
docs/HISTORY.txt
docs/INSTALL.txt
docs/LICENSE.GPL
docs/LICENSE.txt
vs/__init__.py
vs.event.egg-info/PKG-INFO
vs.event.egg-info/SOURCES.txt
vs.event.egg-info/dependency_links.txt
vs.event.egg-info/entry_points.txt
vs.event.egg-info/namespace_packages.txt
vs.event.egg-info/not-zip-safe
vs.event.egg-info/requires.txt
vs.event.egg-info/top_level.txt
vs/event/README.txt
vs/event/__init__.py
vs/event/config.py
vs/event/configure.zcml
vs/event/header.txt
vs/event/interfaces.py
vs/event/setuphandlers.py
vs/event/tests.py
vs/event/usei18ndude.sh
vs/event/browser/__init__.py
vs/event/browser/configure.zcml
vs/event/browser/datepicker.css
vs/event/browser/dtutils.py
vs/event/browser/icalendar.py
vs/event/browser/jquery-ui-custom.js
vs/event/browser/vs-event.css
vs/event/browser/vs_event.py
vs/event/browser/vs_event_view.pt
vs/event/browser/vs_event_view.py
vs/event/content/__init__.py
vs/event/content/configure.zcml
vs/event/content/dtutils.py
vs/event/content/event.py
vs/event/content/event_util.py
vs/event/content/indexing.py
vs/event/content/recurrence.py
vs/event/content/util.py
vs/event/locales/vs.event.pot
vs/event/locales/cz/LC_MESSAGES/vs.event.po
vs/event/locales/de/LC_MESSAGES/vs.event.po
vs/event/locales/it/LC_MESSAGES/vs.event.po
vs/event/profiles/default/catalog.xml
vs/event/profiles/default/cssregistry.xml
vs/event/profiles/default/factorytool.xml
vs/event/profiles/default/import_steps.xml
vs/event/profiles/default/jsregistry.xml
vs/event/profiles/default/metadata.xml
vs/event/profiles/default/types.xml
vs/event/profiles/default/vs.event_various.txt
vs/event/profiles/default/types/VSEvent.xml
vs/event/profiles/default/types/VSSubEvent.xml
vs/event/validators/__init__.py