Metadata-Version: 1.0
Name: vs.event
Version: 0.3.1
Summary: An extended event content-type for Plone (and Plone4Artists calendar)
Home-page: http://svn.plone.org/svn/collective/vs.event
Author: Veit Schiele, Anne Walther, Andreas Jung
Author-email: vs.event@veit-schiele.de
License: GPL
Keywords: Zope Plone Event Recurrence Calendar Plone4Artists
Platform: UNKNOWN
Classifier: Framework :: Plone
Classifier: Framework :: Plone :: 4.0
Classifier: Framework :: Plone :: 4.1
Classifier: Framework :: Plone :: 4.2
Classifier: Programming Language :: Python
Classifier: Topic :: Software Development :: Libraries :: Python Modules
